ips_nequip/__init__.py
ips_nequip/nequip.py
ips_nequip-0.1.0.dist-info/LICENSE
ips_nequip-0.1.0.dist-info/METADATA
ips_nequip-0.1.0.dist-info/WHEEL
ips_nequip-0.1.0.dist-info/RECORD
