Metadata-Version: 2.1
Name: ips-nequip
Version: 0.1.0
Summary: 
Author: PythonFZ
Author-email: fabian.zills@web.de
Requires-Python: >=3.10,<3.12
Classifier: Programming Language :: Python :: 3
Classifier: Programming Language :: Python :: 3.10
Classifier: Programming Language :: Python :: 3.11
Requires-Dist: ipsuite (>=0.1.3,<0.2.0)
Requires-Dist: nequip (>=0.5.6,<0.6.0)
